{"content_schema": {"id": ["self_id@enum", "id", ""], "HealMulti": ["float", "", ""], "FixMulti": ["float", "", ""], "ShieldMulti": ["float", "", ""], "ReloadMulti": ["float", "", ""], "AddPlayBuffs": ["int[]", "", ""]}, "content": {"h1": {"id": "h1", "HealMulti": 0.06, "FixMulti": 0.0, "ShieldMulti": 0.0, "ReloadMulti": 0.0, "AddPlayBuffs": []}, "f1": {"id": "f1", "HealMulti": 0.0, "FixMulti": 0.06, "ShieldMulti": 0.0, "ReloadMulti": 0.0, "AddPlayBuffs": []}, "c1": {"id": "c1", "HealMulti": 0.0, "FixMulti": 0.0, "ShieldMulti": 0.5, "ReloadMulti": 0.0, "AddPlayBuffs": []}, "r1": {"id": "r1", "HealMulti": 0.0, "FixMulti": 0.0, "ShieldMulti": 0.0, "ReloadMulti": 0.8, "AddPlayBuffs": []}, "a1": {"id": "a1", "HealMulti": 0.2, "FixMulti": 0.2, "ShieldMulti": 0.2, "ReloadMulti": 0.0, "AddPlayBuffs": []}}}